best_buy_bullet_bot/.DS_Store
best_buy_bullet_bot/__init__.py
best_buy_bullet_bot/__main__.py
best_buy_bullet_bot/browser.py
best_buy_bullet_bot/command_line.py
best_buy_bullet_bot/utils.py
best_buy_bullet_bot/version.py
best_buy_bullet_bot/audio/__init__.py
best_buy_bullet_bot/audio/notification.wav
best_buy_bullet_bot/audio/sound_effects.py
best_buy_bullet_bot/data/__init__.py
best_buy_bullet_bot/data/browser_login.py
best_buy_bullet_bot/data/setting_utils.py
best_buy_bullet_bot/data/url_utils.py
best_buy_bullet_bot/data/user_data.py
best_buy_bullet_bot/tracker/__init__.py
best_buy_bullet_bot/tracker/progress_bar.py
custom_hooks/__init__.py
custom_hooks/easter_egg.py
3b_bot-1.0.0b3.dist-info/LICENSE
3b_bot-1.0.0b3.dist-info/METADATA
3b_bot-1.0.0b3.dist-info/WHEEL
3b_bot-1.0.0b3.dist-info/entry_points.txt
3b_bot-1.0.0b3.dist-info/top_level.txt
3b_bot-1.0.0b3.dist-info/RECORD
