Metadata-Version: 2.1
Name: 3b-bot
Version: 1.0.0b3
Summary: Quickly purchase items from Best Buy the moment they restock.
Home-page: https://github.com/LeonShams/BestBuyBulletBot
Author: Leon Shams-Schaal
License: MIT
Project-URL: Documentation, https://github.com/LeonShams/BestBuyBulletBot/wiki
Project-URL: Bug Tracker, https://github.com/LeonShams/BestBuyBulletBot/issues
Keywords: bestbuy bot bestbuybot bestbuybulletbot 3bbot 3b-bot bestbuystock         bestbuyrestock bestbuytracker stocktracker bestbuystocktracker         autocheckout bestbuyautocheckout nvidiabot gpubot nvidiagpubot         3060bot 3060tibot 3070bot 3070tibot 3080bot 3080tibot 3090bot         ps5bot nvidiatracker gputracker nvidiagputracker 3060tracker         3060titracker 3070tracker 3070titracker 3080tracker 3080titracker         3090tracker ps5tracker
Platform: UNKNOWN
Classifier: Development Status :: 4 - Beta
Classifier: Intended Audience :: End Users/Desktop
Classifier: Operating System :: OS Independent
Classifier: License :: OSI Approved :: MIT License
Classifier: Programming Language :: Python :: 3
Classifier: Programming Language :: Python :: 3 :: Only
Classifier: Environment :: Console
Requires-Python: >=3.6
Requires-Dist: beautifulsoup4 (>=4.6.3)
Requires-Dist: clipboard (>=0.0.4)
Requires-Dist: elevate (>=0.1.3)
Requires-Dist: keyring (>=20.0.0)
Requires-Dist: keyrings.cryptfile (>=1.3.8)
Requires-Dist: playsound (>=1.2.2)
Requires-Dist: psutil (>=5.0.0)
Requires-Dist: requests (>=2.15.0)
Requires-Dist: rich (>=10.0.1)
Requires-Dist: selenium (==3.141.0)
Requires-Dist: webdriver-manager (>=3.0.0)
